s3async/__init__.py
s3async/console.py
s3async/copy.py
s3async/delete.py
s3async/get.py
s3async/list.py
s3async/log.py
s3async/model.py
s3async/put.py
s3async/py.typed
s3async/sync.py
s3async/tag.py
s3async/utils.py
s3async-1.0.0.dist-info/LICENSE.md
s3async-1.0.0.dist-info/METADATA
s3async-1.0.0.dist-info/WHEEL
s3async-1.0.0.dist-info/entry_points.txt
s3async-1.0.0.dist-info/RECORD
