Metadata-Version: 2.1
Name: s3async
Version: 1.0.0
Summary: Helper functions for interacting with s3.
License: MIT
Author: Arsi Juote
Author-email: arsi.juote@advian.fi
Requires-Python: >=3.9,<4.0
Classifier: License :: OSI Approved :: MIT License
Classifier: Programming Language :: Python :: 3
Classifier: Programming Language :: Python :: 3.9
Classifier: Programming Language :: Python :: 3.10
Classifier: Programming Language :: Python :: 3.11
Classifier: Programming Language :: Python :: 3.12
Requires-Dist: aiobotocore[boto3] (>=2.2.0,<3.0.0)
Requires-Dist: aiofiles (>=0.8.0,<0.9.0)
Requires-Dist: click (>=8.0,<9.0)
